gm3etl/__init__.py
gm3etl-0.0.1.dist-info/DESCRIPTION.rst
gm3etl-0.0.1.dist-info/METADATA
gm3etl-0.0.1.dist-info/RECORD
gm3etl-0.0.1.dist-info/WHEEL
gm3etl-0.0.1.dist-info/metadata.json
gm3etl-0.0.1.dist-info/top_level.txt
