Metadata-Version: 2.0
Name: gm3etl
Version: 0.0.1
Summary: gm3etl
Home-page: http://myquant.cn/
Author: myquant_dev
Author-email: support@myquant.cn
License: Apache 2.0
Platform: UNKNOWN
Classifier: Development Status :: 4 - Beta
Classifier: Intended Audience :: Developers
Classifier: License :: OSI Approved :: Apache Software License
Classifier: Programming Language :: Python :: 2.7
Classifier: Programming Language :: Python :: 3.5
Classifier: Programming Language :: Python :: 3.6
Classifier: Topic :: Software Development :: Libraries :: Python Modules
